pydyf/__init__.py
pydyf-0.4.0.dist-info/LICENSE
pydyf-0.4.0.dist-info/WHEEL
pydyf-0.4.0.dist-info/METADATA
pydyf-0.4.0.dist-info/RECORD
