Metadata-Version: 2.1
Name: pydyf
Version: 0.4.0
Summary: A low-level PDF generator.
Keywords: pdf,generator
Author-email: CourtBouillon <contact@courtbouillon.org>
Maintainer-email: CourtBouillon <contact@courtbouillon.org>
Requires-Python: >=3.7
Classifier: Development Status :: 4 - Beta
Classifier: Intended Audience :: Developers
Classifier: License :: OSI Approved :: BSD License
Classifier: Operating System :: OS Independent
Classifier: Programming Language :: Python
Classifier: Programming Language :: Python :: 3
Classifier: Programming Language :: Python :: 3 :: Only
Classifier: Programming Language :: Python :: 3.7
Classifier: Programming Language :: Python :: 3.8
Classifier: Programming Language :: Python :: 3.9
Classifier: Programming Language :: Python :: 3.10
Classifier: Programming Language :: Python :: Implementation :: CPython
Classifier: Programming Language :: Python :: Implementation :: PyPy
Requires-Dist: sphinx ; extra == "doc"
Requires-Dist: sphinx_rtd_theme ; extra == "doc"
Requires-Dist: pytest ; extra == "test"
Requires-Dist: isort ; extra == "test"
Requires-Dist: flake8 ; extra == "test"
Requires-Dist: pillow ; extra == "test"
Project-URL: Changelog, https://github.com/CourtBouillon/pydyf/releases
Project-URL: Code, https://github.com/CourtBouillon/pydyf
Project-URL: Documentation, https://doc.courtbouillon.org/pydyf/
Project-URL: Donation, https://opencollective.com/courtbouillon
Project-URL: Homepage, https://www.courtbouillon.org/pydyf
Project-URL: Issues, https://github.com/CourtBouillon/pydyf/issues
Provides-Extra: doc
Provides-Extra: test
